grapl_analyzerlib/__init__.py
grapl_analyzerlib/analyzer.py
grapl_analyzerlib/comparators.py
grapl_analyzerlib/counters.py
grapl_analyzerlib/execution.py
grapl_analyzerlib/extendable.py
grapl_analyzerlib/grapl_client.py
grapl_analyzerlib/node_types.py
grapl_analyzerlib/plugin_retriever.py
grapl_analyzerlib/prelude.py
grapl_analyzerlib/py.typed
grapl_analyzerlib/query_gen.py
grapl_analyzerlib/queryable.py
grapl_analyzerlib/retry.py
grapl_analyzerlib/schema.py
grapl_analyzerlib/subgraph_view.py
grapl_analyzerlib/view_from_proto.py
grapl_analyzerlib/viewable.py
grapl_analyzerlib/nodes/__init__.py
grapl_analyzerlib/nodes/asset.py
grapl_analyzerlib/nodes/base.py
grapl_analyzerlib/nodes/engagement.py
grapl_analyzerlib/nodes/entity.py
grapl_analyzerlib/nodes/file.py
grapl_analyzerlib/nodes/ip_address.py
grapl_analyzerlib/nodes/ip_connection.py
grapl_analyzerlib/nodes/ip_port.py
grapl_analyzerlib/nodes/lens.py
grapl_analyzerlib/nodes/network_connection.py
grapl_analyzerlib/nodes/process.py
grapl_analyzerlib/nodes/process_inbound_connection.py
grapl_analyzerlib/nodes/process_outbound_connection.py
grapl_analyzerlib/nodes/risk.py
grapl_analyzerlib-0.2.72.dist-info/METADATA
grapl_analyzerlib-0.2.72.dist-info/WHEEL
grapl_analyzerlib-0.2.72.dist-info/namespace_packages.txt
grapl_analyzerlib-0.2.72.dist-info/top_level.txt
grapl_analyzerlib-0.2.72.dist-info/RECORD
